httpsig/__init__.py
httpsigpy-0.0.8.dist-info/LICENSE
httpsigpy-0.0.8.dist-info/METADATA
httpsigpy-0.0.8.dist-info/WHEEL
httpsigpy-0.0.8.dist-info/top_level.txt
httpsigpy-0.0.8.dist-info/RECORD
