Metadata-Version: 2.1
Name: httpsigpy
Version: 0.0.8
Summary: HTTP Message Signatures
Home-page: https://github.com/bspkio/httpsigpy
Author: Justin Richer
Author-email: python@justin.richer.org
Classifier: Programming Language :: Python :: 3
Classifier: License :: OSI Approved :: MIT License
Classifier: Operating System :: OS Independent
Requires-Python: >=3.8
License-File: LICENSE
